ipchanger/__init__.py
ipchanger/__main__.py
ipchanger/cli.py
ipchanger/client.py
ipchanger/rsa.py
ipchanger/test_client.py
ipchanger/test_rsa.py
ipchanger/urls.py
tibia_ipchanger-0.1.2.dist-info/entry_points.txt
tibia_ipchanger-0.1.2.dist-info/LICENSE
tibia_ipchanger-0.1.2.dist-info/WHEEL
tibia_ipchanger-0.1.2.dist-info/METADATA
tibia_ipchanger-0.1.2.dist-info/RECORD
